pantsbuild.pants.contrib.errorprone-1.28.0-py3.6-nspkg.pth
pants/contrib/errorprone/__init__.py
pants/contrib/errorprone/register.py
pants/contrib/errorprone/tasks/__init__.py
pants/contrib/errorprone/tasks/errorprone.py
pantsbuild.pants.contrib.errorprone-1.28.0.dist-info/METADATA
pantsbuild.pants.contrib.errorprone-1.28.0.dist-info/WHEEL
pantsbuild.pants.contrib.errorprone-1.28.0.dist-info/entry_points.txt
pantsbuild.pants.contrib.errorprone-1.28.0.dist-info/namespace_packages.txt
pantsbuild.pants.contrib.errorprone-1.28.0.dist-info/top_level.txt
pantsbuild.pants.contrib.errorprone-1.28.0.dist-info/zip-safe
pantsbuild.pants.contrib.errorprone-1.28.0.dist-info/RECORD
